config/__init__.py
config/config_menubar.py
config/settings.py
config/settings_1.py
config/settings_2.py
vunghixuan/__init__.py
vunghixuan/api_and_otp.py
vunghixuan/create_files_for_package.py
vunghixuan/gui_main.py
vunghixuan/login.py
vunghixuan/main.py
vunghixuan/project.py
vunghixuan/setting_controlls.py
vunghixuan/settings.py
vunghixuan-0.1.6.dist-info/METADATA
vunghixuan-0.1.6.dist-info/WHEEL
vunghixuan-0.1.6.dist-info/entry_points.txt
vunghixuan-0.1.6.dist-info/top_level.txt
vunghixuan-0.1.6.dist-info/RECORD
