Metadata-Version: 2.1
Name: vunghixuan
Version: 0.1.6
Summary: Get API, OTP, Create Project
Home-page: https://github.com/VuNghiXuan/pypi_package
Author: Đặng Thanh Vũ
Author-email: vunghixuan.info@gmail.com
License: MIT
Classifier: Programming Language :: Python :: 3
Classifier: License :: OSI Approved :: MIT License
Classifier: Operating System :: OS Independent
Requires-Python: >=3.11
Requires-Dist: pyotp==2.9.0
Requires-Dist: PySide6==6.8.0.1
Requires-Dist: PySide6-Addons==6.8.0.1
Requires-Dist: PySide6-Essentials==6.8.0.1
Requires-Dist: shiboken6==6.8.0.1
Requires-Dist: SQLAlchemy==2.0.36
Requires-Dist: typing-extensions==4.12.2
